{"stats":{"minecraft:killed_by":{"minecraft:zombie":1,"minecraft:player":94},"minecraft:dropped":{"minecraft:spectral_arrow":1,"minecraft:netherite_hoe":1,"minecraft:blaze_powder":1,"minecraft:lapis_lazuli":2,"minecraft:oak_sign":1,"minecraft:blue_ice":2,"minecraft:bone":771},"minecraft:used":{"minecraft:shield":7},"minecraft:picked_up":{"minecraft:anvil":1,"minecraft:bone":771,"minecraft:oak_sign":2,"minecraft:netherite_sword":1,"minecraft:blue_ice":2,"minecraft:spectral_arrow":1,"minecraft:netherite_hoe":1,"minecraft:blaze_powder":1,"minecraft:lapis_lazuli":2},"minecraft:custom":{"minecraft:time_since_rest":2,"minecraft:crouch_one_cm":50163,"minecraft:sprint_one_cm":202962,"minecraft:play_time":108172,"minecraft:deaths":682,"minecraft:damage_taken":40592,"minecraft:walk_one_cm":275422,"minecraft:sneak_time":16236,"minecraft:damage_blocked_by_shield":386,"minecraft:walk_under_water_one_cm":1417,"minecraft:mob_kills":3,"minecraft:drop":155,"minecraft:jump":1808,"minecraft:damage_dealt":608,"minecraft:leave_game":2,"minecraft:walk_on_water_one_cm":13717,"minecraft:time_since_death":1,"minecraft:climb_one_cm":0,"minecraft:total_world_time":108172,"minecraft:swim_one_cm":256,"minecraft:fall_one_cm":344056,"minecraft:fly_one_cm":346847,"minecraft:player_kills":26}},"DataVersion":3218}